<annotation>
	<folder>headlights</folder>
	<filename>frame_8320.jpg</filename>
	<path>/headlights/frame_8320.jpg</path>
	<source>
		<database>Unspecified</database>
	</source>
	<size>
		<width>1920</width>
		<height>1080</height>
		<depth>3</depth>
	</size>
	<object>
		<name>four wheeler</name>
		<pose>Unspecified</pose>
		<truncated>0</truncated>
		<difficult>0</difficult>
		<bndbox>
			<xmin>1031</xmin>
			<ymin>522</ymin>
			<xmax>1143</xmax>
			<ymax>634</ymax>
		</bndbox>
	</object>
	<object>
		<name>two wheeler</name>
		<pose>Unspecified</pose>
		<truncated>0</truncated>
		<difficult>0</difficult>
		<bndbox>
			<xmin>988</xmin>
			<ymin>573</ymin>
			<xmax>1018</xmax>
			<ymax>619</ymax>
		</bndbox>
	</object>
	<object>
		<name>headlight</name>
		<pose>Unspecified</pose>
		<truncated>0</truncated>
		<difficult>0</difficult>
		<bndbox>
			<xmin>1043</xmin>
			<ymin>572</ymin>
			<xmax>1101</xmax>
			<ymax>627</ymax>
		</bndbox>
	</object>
	<object>
		<name>headlight</name>
		<pose>Unspecified</pose>
		<truncated>0</truncated>
		<difficult>0</difficult>
		<bndbox>
			<xmin>1109</xmin>
			<ymin>576</ymin>
			<xmax>1139</xmax>
			<ymax>622</ymax>
		</bndbox>
	</object>
	<object>
		<name>headlight</name>
		<pose>Unspecified</pose>
		<truncated>0</truncated>
		<difficult>0</difficult>
		<bndbox>
			<xmin>992</xmin>
			<ymin>583</ymin>
			<xmax>1010</xmax>
			<ymax>606</ymax>
		</bndbox>
	</object>
</annotation>